LICENSE
MANIFEST.in
README.rst
rswt.py
setup.py
rswt.egg-info/PKG-INFO
rswt.egg-info/SOURCES.txt
rswt.egg-info/dependency_links.txt
rswt.egg-info/requires.txt
rswt.egg-info/top_level.txt